miso20022/__init__.py
miso20022/cli.py
miso20022/fedwire.py
miso20022/helpers.py
miso20022/bah/__init__.py
miso20022/bah/apphdr.py
miso20022/common/__init__.py
miso20022/common/account.py
miso20022/common/customer.py
miso20022/common/payment.py
miso20022/pacs/__init__.py
miso20022/pacs/pacs002.py
miso20022/pacs/pacs008.py
miso20022/pacs/pacs028.py
miso20022-0.1.6.dist-info/licenses/LICENSE
miso20022-0.1.6.dist-info/METADATA
miso20022-0.1.6.dist-info/WHEEL
miso20022-0.1.6.dist-info/entry_points.txt
miso20022-0.1.6.dist-info/top_level.txt
miso20022-0.1.6.dist-info/RECORD
