Metadata-Version: 2.4
Name: miso20022
Version: 0.1.6
Summary: ISO 20022 Message Generator for US Payment Rails
Author-email: Sai Vatsavai <sai.vatsavai@mbanq.com>, Vamsi Krishna <vamsi.krishna@mbanq.com>, Mbanq <developers@mbanq.com>
License-Expression: Apache-2.0
Project-URL: Homepage, https://github.com/Mbanq/iso20022
Project-URL: Bug Tracker, https://github.com/Mbanq/iso20022/issues
Keywords: iso20022,financial,messaging,banking,fedwire,us payment rails,fednow
Classifier: Development Status :: 3 - Alpha
Classifier: Intended Audience :: Financial and Insurance Industry
Classifier: Programming Language :: Python :: 3
Classifier: Programming Language :: Python :: 3.7
Classifier: Programming Language :: Python :: 3.8
Classifier: Programming Language :: Python :: 3.9
Classifier: Programming Language :: Python :: 3.10
Classifier: Topic :: Office/Business :: Financial
Classifier: Topic :: Software Development :: Libraries :: Python Modules
Requires-Python: >=3.7
License-File: LICENSE
Requires-Dist: xmlschema>=1.9.0
Requires-Dist: python-dotenv>=0.19.0
Requires-Dist: xmltodict>=0.13.0
Requires-Dist: lxml>=4.9.0
Requires-Dist: setuptools~=58.0.4
Provides-Extra: webapp
Requires-Dist: flask; extra == "webapp"
Requires-Dist: xmltodict; extra == "webapp"
Dynamic: license-file
